{
    "data": {
        "title": "Ruby",
        "cards": [
            {
                "question": "Ruby 1",
                "hint": "Ruby Hint 1",
                "answer": "Ruby Answer 1"
            },
            {
                "question": "Ruby 2",
                "hint": "Ruby Hint 2",
                "answer": "Ruby Answer 2"
            },
            {
                "question": "Ruby 3",
                "hint": "Ruby Hint 3",
                "answer": "Ruby Answer 3"
            },
            {
                "question": "Ruby 4",
                "hint": "Ruby Hint 4",
                "answer": "RubyAnswer 4"
            },
            {
                "question": "Ruby5",
                "hint": "Ruby Hint 5",
                "answer": "RubyAnswer 5"
            }
        ]
    }
}